etsi/fliplist/__init__.py
etsi/fliplist/cli.py
etsi/fliplist/core.py
etsi/fliplist/utils.py
etsi_fliplist-0.1.1.dist-info/licenses/LICENSE
etsi_fliplist-0.1.1.dist-info/METADATA
etsi_fliplist-0.1.1.dist-info/WHEEL
etsi_fliplist-0.1.1.dist-info/top_level.txt
etsi_fliplist-0.1.1.dist-info/RECORD
